maoplotlib/__init__.py
maoplotlib/all.py
maoplotlib/ml.py
maoplotlib/ml3.py
maoplotlib/testing.py
maoplotlib-0.0.10.dist-info/METADATA
maoplotlib-0.0.10.dist-info/WHEEL
maoplotlib-0.0.10.dist-info/top_level.txt
maoplotlib-0.0.10.dist-info/RECORD
